smfish_image_processing/ReaderROI.class
smfish_image_processing/ReaderROI.java
smfish_image_processing/ReaderROIList.class
smfish_image_processing/ReaderROIList.java
smfish_image_processing/__init__.py
smfish_image_processing/do_all_stitch.py
smfish_image_processing/finished
smfish_image_processing/ij.jar
smfish_image_processing/image_processing.py
smfish_image_processing/read_css_template.py
smfish_image_processing/read_html_template.py
smfish_image_processing/segmentation.py
smfish_image_processing/smfish_read_config.py
smfish_image_processing/smfish_step1_setup.py
smfish_image_processing/stitch_cell_centroid.py
smfish_image_processing-1.4.4.dist-info/METADATA
smfish_image_processing-1.4.4.dist-info/WHEEL
smfish_image_processing-1.4.4.dist-info/entry_points.txt
smfish_image_processing-1.4.4.dist-info/top_level.txt
smfish_image_processing-1.4.4.dist-info/RECORD
