Metadata-Version: 2.1
Name: smfish-image-processing
Version: 1.4.4
Summary: SmFISH image processing library including image stitching, rotation, scaling tools
Home-page: https://bitbucket.org/qzhu/smfish-image-processing
Author: Qian Zhu
Author-email: zqian@jimmy.harvard.edu
License: UNKNOWN
Platform: UNKNOWN
Classifier: Programming Language :: Python :: 3
Classifier: License :: OSI Approved :: MIT License
Classifier: Operating System :: OS Independent
Requires-Python: >=3.5
Requires-Dist: scipy
Requires-Dist: numpy
Requires-Dist: pandas
Requires-Dist: seaborn
Requires-Dist: matplotlib
Requires-Dist: tifffile
